main.py
src/__init__.py
src/cli/__init__.py
src/cli/ascii_art.py
src/cli/commands.py
src/generators/__init__.py
src/generators/basehandler.py
src/generators/dryrunhandler.py
src/generators/handler.py
src/generators/datatypes/__init__.py
src/generators/datatypes/fakerproxy.py
src/generators/datatypes/sequence.py
src/generators/datatypes/sequence_timestamp.py
src/generators/datatypes/faker_custom/__init__.py
src/generators/datatypes/faker_custom/address/__init__.py
src/generators/datatypes/faker_custom/address/pt_BR/__init__.py
src/generators/datatypes/faker_custom/company/__init__.py
src/generators/datatypes/faker_custom/company/pt_BR/__init__.py
src/generators/datatypes/faker_custom/ssn/__init__.py
src/generators/datatypes/faker_custom/ssn/pt_BR/__init__.py
src/lib/__init__.py
src/lib/shell.py
src/lib/sql.py
src/lib/config/__init__.py
src/lib/config/fields.py
src/lib/config/formatters.py
src/lib/config/inspector.py
src/lib/config/serializers.py
src/lib/formatters/__init__.py
src/lib/formatters/csv.py
src/lib/formatters/json.py
src/lib/formatters/sql.py
src/lib/mysql/__init__.py
src/lib/mysql/mysql.py
src/lib/postgresql/__init__.py
src/lib/postgresql/psql.py
src/lib/writers/__init__.py
src/lib/writers/file.py
src/lib/writers/databases/__init__.py
src/lib/writers/databases/mysql.py
src/lib/writers/databases/postgresql.py
src/lib/writers/remotes/__init__.py
src/lib/writers/remotes/azure_bs.py
src/lib/writers/remotes/gcs.py
src/lib/writers/remotes/gcs_presigned_url.py
src/lib/writers/remotes/s3.py
src/lib/writers/remotes/s3_presigned_url.py
src/tests/__init__.py
src/tests/cli/__init__.py
src/tests/cli/cli_fixture.py
src/tests/cli/test_cli.py
src/tests/generators/__init__.py
src/tests/generators/handler_fixtures.py
src/tests/generators/test_basehundler.py
src/tests/generators/test_dryrun.py
src/tests/generators/test_handler.py
src/tests/generators/datatypes/__init__.py
src/tests/generators/datatypes/generators_fixtures.py
src/tests/generators/datatypes/test_sequence.py
ggenerator-0.3.dist-info/LICENSE
ggenerator-0.3.dist-info/METADATA
ggenerator-0.3.dist-info/WHEEL
ggenerator-0.3.dist-info/entry_points.txt
ggenerator-0.3.dist-info/top_level.txt
ggenerator-0.3.dist-info/RECORD
