Metadata-Version: 2.1
Name: ggenerator
Version: 0.3
Summary: A tool capable to generate fake data with a given specification defined as a JSON DSL
Home-page: https://datenworks.com/
Author: Datenworks
Author-email: contato@datenworks.com
License: MIT
Project-URL: Source Code, https://github.com/Datenworks/ggenerator
Platform: UNKNOWN
Requires-Dist: python-dateutil (>=2.8.1)
Requires-Dist: pandas (>=1.0.1)
Requires-Dist: click (>=7.1.1)
Requires-Dist: tabulate (>=0.8.6)
Requires-Dist: requests (>=2.23.0)
Requires-Dist: gcsfs (>=0.6.0)
Requires-Dist: s3fs (>=0.4.0)
Requires-Dist: faker (>=4.0.1)
Requires-Dist: sqlalchemy (>=1.3.16)
Requires-Dist: mysql-connector-python (>=8.0.19)
Requires-Dist: alive-progress (>=1.5.1)
Requires-Dist: azure-storage-blob (>=12.3.0)
Requires-Dist: psycopg2-binary (>=2.8.5)
Provides-Extra: mysql
Requires-Dist: mysqlclient (>=1.4.6) ; extra == 'mysql'
